tissue_tag/__init__.py
tissue_tag/tissue_tag.py
tissue_tag-0.2.2.dist-info/LICENSE
tissue_tag-0.2.2.dist-info/METADATA
tissue_tag-0.2.2.dist-info/WHEEL
tissue_tag-0.2.2.dist-info/top_level.txt
tissue_tag-0.2.2.dist-info/RECORD
