Metadata-Version: 2.1
Name: tissue-tag
Version: 0.2.2
Summary: Tissue Tag: jupyter image annotator
Home-page: https://github.com/nadavyayon/TissueTag
Author: Oren Amsalem, Nadav Yayon, Andrian Yang
Author-email: ny1@sanger.ac.uk
Classifier: Programming Language :: Python :: 3
Classifier: Operating System :: OS Independent
License-File: LICENSE
Requires-Dist: opencv-python
Requires-Dist: Pillow
Requires-Dist: bokeh
Requires-Dist: jupyter-bokeh
Requires-Dist: matplotlib
Requires-Dist: seaborn
Requires-Dist: scipy
Requires-Dist: scikit-image
Requires-Dist: tqdm
Requires-Dist: scikit-learn
Requires-Dist: holoviews
Requires-Dist: datashader
Requires-Dist: panel ==1.3.8
Requires-Dist: jupyterlab
